dumpconfluence/__init__.py
dumpconfluence/__main__.py
dumpconfluence/cli.py
dumpconfluence/config.py
dumpconfluence/core.py
dumpconfluence/exceptions.py
dumpconfluence-1.0.1.dist-info/licenses/LICENSE
dumpconfluence-1.0.1.dist-info/METADATA
dumpconfluence-1.0.1.dist-info/WHEEL
dumpconfluence-1.0.1.dist-info/entry_points.txt
dumpconfluence-1.0.1.dist-info/top_level.txt
dumpconfluence-1.0.1.dist-info/RECORD
